<annotation>
	<folder>tiramisu</folder>
	<filename>96202.jpg</filename>
	<path>E:\food-101\food-101\images\tiramisu\96202.jpg</path>
	<source>
		<database>Unknown</database>
	</source>
	<size>
		<width>512</width>
		<height>384</height>
		<depth>3</depth>
	</size>
	<segmented>0</segmented>
	<object>
		<name>tiramisu</name>
		<pose>Unspecified</pose>
		<truncated>0</truncated>
		<difficult>0</difficult>
		<bndbox>
			<xmin>172</xmin>
			<ymin>99</ymin>
			<xmax>321</xmax>
			<ymax>308</ymax>
		</bndbox>
	</object>
</annotation>
