<annotation>
	<folder>deviled_eggs</folder>
	<filename>3123467.jpg</filename>
	<path>/media/ebrahim/5BC7-42751/colege/project/dataset/deviled_eggs-20200805T232011Z-001/deviled_eggs/3123467.jpg</path>
	<source>
		<database>Unknown</database>
	</source>
	<size>
		<width>512</width>
		<height>512</height>
		<depth>3</depth>
	</size>
	<segmented>0</segmented>
	<object>
		<name>deviled_eggs</name>
		<pose>Unspecified</pose>
		<truncated>0</truncated>
		<difficult>0</difficult>
		<bndbox>
			<xmin>175</xmin>
			<ymin>10</ymin>
			<xmax>271</xmax>
			<ymax>93</ymax>
		</bndbox>
	</object>
	<object>
		<name>deviled_eggs</name>
		<pose>Unspecified</pose>
		<truncated>0</truncated>
		<difficult>0</difficult>
		<bndbox>
			<xmin>170</xmin>
			<ymin>90</ymin>
			<xmax>286</xmax>
			<ymax>203</ymax>
		</bndbox>
	</object>
	<object>
		<name>deviled_eggs</name>
		<pose>Unspecified</pose>
		<truncated>0</truncated>
		<difficult>0</difficult>
		<bndbox>
			<xmin>172</xmin>
			<ymin>204</ymin>
			<xmax>298</xmax>
			<ymax>333</ymax>
		</bndbox>
	</object>
	<object>
		<name>deviled_eggs</name>
		<pose>Unspecified</pose>
		<truncated>0</truncated>
		<difficult>0</difficult>
		<bndbox>
			<xmin>168</xmin>
			<ymin>354</ymin>
			<xmax>316</xmax>
			<ymax>503</ymax>
		</bndbox>
	</object>
</annotation>
