<annotation>
	<folder>sushi</folder>
	<filename>45573.jpg</filename>
	<path>E:\Beshoy\College\content\food-101\images\sushi\45573.jpg</path>
	<source>
		<database>Unknown</database>
	</source>
	<size>
		<width>384</width>
		<height>512</height>
		<depth>3</depth>
	</size>
	<segmented>0</segmented>
	<object>
		<name>sushi</name>
		<pose>Unspecified</pose>
		<truncated>0</truncated>
		<difficult>0</difficult>
		<bndbox>
			<xmin>71</xmin>
			<ymin>117</ymin>
			<xmax>341</xmax>
			<ymax>427</ymax>
		</bndbox>
	</object>
</annotation>
