<annotation>
	<folder>fried_rice</folder>
	<filename>1784142.jpg</filename>
	<path>/media/ebrahim/5BC7-42751/colege/project/dataset/fried_rice-20200805T171833Z-001/fried_rice/1784142.jpg</path>
	<source>
		<database>Unknown</database>
	</source>
	<size>
		<width>512</width>
		<height>419</height>
		<depth>3</depth>
	</size>
	<segmented>0</segmented>
	<object>
		<name>fried_rice</name>
		<pose>Unspecified</pose>
		<truncated>0</truncated>
		<difficult>0</difficult>
		<bndbox>
			<xmin>102</xmin>
			<ymin>4</ymin>
			<xmax>327</xmax>
			<ymax>202</ymax>
		</bndbox>
	</object>
	<object>
		<name>fried_rice</name>
		<pose>Unspecified</pose>
		<truncated>0</truncated>
		<difficult>0</difficult>
		<bndbox>
			<xmin>143</xmin>
			<ymin>193</ymin>
			<xmax>334</xmax>
			<ymax>368</ymax>
		</bndbox>
	</object>
</annotation>
