<annotation>
	<folder>fried_rice</folder>
	<filename>3555295.jpg</filename>
	<path>/media/ebrahim/5BC7-42751/colege/project/dataset/fried_rice-20200805T171833Z-001/fried_rice/3555295.jpg</path>
	<source>
		<database>Unknown</database>
	</source>
	<size>
		<width>512</width>
		<height>384</height>
		<depth>3</depth>
	</size>
	<segmented>0</segmented>
	<object>
		<name>fried_rice</name>
		<pose>Unspecified</pose>
		<truncated>0</truncated>
		<difficult>0</difficult>
		<bndbox>
			<xmin>88</xmin>
			<ymin>30</ymin>
			<xmax>469</xmax>
			<ymax>365</ymax>
		</bndbox>
	</object>
</annotation>
